pymanip/__init__.py
pymanip/__main__.py
pymanip/asynctools.py
pymanip/collection.py
pymanip/mytime.py
pymanip/aiodaq/__init__.py
pymanip/aiodaq/arduino.py
pymanip/aiodaq/daqmx.py
pymanip/aiodaq/scope.py
pymanip/aioinstruments/__init__.py
pymanip/aioinstruments/agilent_34970a.py
pymanip/aioinstruments/agilent_6030a.py
pymanip/aioinstruments/aiodrivers.py
pymanip/aioinstruments/aiofeatures.py
pymanip/aioinstruments/aioiec60488.py
pymanip/aioinstruments/aiosocket.py
pymanip/aioinstruments/arduino_gbf.py
pymanip/aioinstruments/cryocon_24c.py
pymanip/aioinstruments/julabo.py
pymanip/aioinstruments/lakeshore_224.py
pymanip/aioinstruments/lauda.py
pymanip/aioinstruments/newport_xps_rl.py
pymanip/aioinstruments/srs_ds360.py
pymanip/aioinstruments/stanford_sr830.py
pymanip/aioinstruments/tdk_lambda.py
pymanip/aioinstruments/tti_cpx400dp.py
pymanip/aioinstruments/xantrex_xdc300.py
pymanip/aiosession/__init__.py
pymanip/aiosession/aiosession.py
pymanip/aiosession/database_v1.py
pymanip/aiosession/database_v3.py
pymanip/aiosession/database_v4.py
pymanip/aiosession/test_aiosession.py
pymanip/asyncsession/__init__.py
pymanip/asyncsession/asyncsession.py
pymanip/asyncsession/database_v1.py
pymanip/asyncsession/database_v3.py
pymanip/asyncsession/database_v4.py
pymanip/asyncsession/remoteobserver.py
pymanip/asyncsession/savedasyncsession.py
pymanip/asyncsession/test_asyncsession.py
pymanip/asyncsession/web/__init__.py
pymanip/asyncsession/web/email.html
pymanip/asyncsession/web/layout.html
pymanip/asyncsession/web/main.html
pymanip/asyncsession/web/plot.html
pymanip/asyncsession/web_static/Chart.bundle.js
pymanip/asyncsession/web_static/__init__.py
pymanip/daq/DAQmx.py
pymanip/daq/PXI.py
pymanip/daq/Scope.py
pymanip/daq/__init__.py
pymanip/instruments/__init__.py
pymanip/instruments/fluidlab_instruments.py
pymanip/interfaces/__init__.py
pymanip/interfaces/aiogpib.py
pymanip/interfaces/aiointer.py
pymanip/interfaces/aioserial.py
pymanip/interfaces/aiovisa.py
pymanip-0.4.4.dist-info/licenses/LICENSE.txt
pymanip-0.4.4.dist-info/METADATA
pymanip-0.4.4.dist-info/WHEEL
pymanip-0.4.4.dist-info/top_level.txt
pymanip-0.4.4.dist-info/RECORD
