Metadata-Version: 2.4
Name: pymanip
Version: 0.4.4
Summary: Python framework for experiments
Home-page: https://pypi.org/project/pymanip/
Author: Julien Salort
Author-email: julien.salort@ens-lyon.fr
License: CeCILL-B
Project-URL: Documentation, https://pymanip.readthedocs.io/en/latest/
Project-URL: Source Code, https://github.com/jsalort/pymanip
Classifier: Programming Language :: Python :: 3
Classifier: Operating System :: OS Independent
License-File: LICENSE.txt
Requires-Dist: h5py
Requires-Dist: fluiddyn>=0.3.2
Requires-Dist: fluidlab>=0.1.0
Requires-Dist: progressbar2
Requires-Dist: aiohttp
Requires-Dist: aiohttp_jinja2
Requires-Dist: pyvisa
Requires-Dist: sqlalchemy
Requires-Dist: qasync
Requires-Dist: pytest-asyncio
Requires-Dist: aiofile
Requires-Dist: aiosqlite
Requires-Dist: greenlet
Requires-Dist: pyqtgraph
Dynamic: license-file
